{
  "project_info": {
    "project_number": "250773787739",
    "project_id": "task-management-88635",
    "storage_bucket": "task-management-88635.firebasestorage.app"
  },
  "client": [
    {
      "client_info": {
        "mobilesdk_app_id": "1:250773787739:android:9c9ad169aac7238aff9b7e",
        "android_client_info": {
          "package_name": "com.developersHub.task_management_app"
        }
      },
      "oauth_client": [],
      "api_key": [
        {
          "current_key": "AIzaSyC6YKRcyelZN3c-MmiqYJXFRTrpKDli13k"
        }
      ],
      "services": {
        "appinvite_service": {
          "other_platform_oauth_client": []
        }
      }
    }
  ],
  "configuration_version": "1"
}